airflow_kubernetes_job_operator/__init__.py
airflow_kubernetes_job_operator/collections.py
airflow_kubernetes_job_operator/config.py
airflow_kubernetes_job_operator/exceptions.py
airflow_kubernetes_job_operator/job_runner.py
airflow_kubernetes_job_operator/kubernetes_job_operator.py
airflow_kubernetes_job_operator/kubernetes_job_operator.py.default.yaml
airflow_kubernetes_job_operator/kubernetes_legacy_job_operator.py
airflow_kubernetes_job_operator/kubernetes_legacy_pod_generators.py
airflow_kubernetes_job_operator/utils.py
airflow_kubernetes_job_operator/kube_api/__init__.py
airflow_kubernetes_job_operator/kube_api/client.py
airflow_kubernetes_job_operator/kube_api/collections.py
airflow_kubernetes_job_operator/kube_api/config.py
airflow_kubernetes_job_operator/kube_api/exceptions.py
airflow_kubernetes_job_operator/kube_api/operations.py
airflow_kubernetes_job_operator/kube_api/queries.py
airflow_kubernetes_job_operator/kube_api/utils.py
airflow_kubernetes_job_operator/kube_api/watchers.py
airflow_kubernetes_job_operator/templates/job_default.yaml
airflow_kubernetes_job_operator/templates/pod_default.yaml
airflow_kubernetes_job_operator_test11-0.1.dist-info/METADATA
airflow_kubernetes_job_operator_test11-0.1.dist-info/WHEEL
airflow_kubernetes_job_operator_test11-0.1.dist-info/top_level.txt
airflow_kubernetes_job_operator_test11-0.1.dist-info/RECORD
